mt3/__init__.py
mt3/student.py
mt3/thompson.py
mt3-0.2.1.dist-info/entry_points.txt
mt3-0.2.1.dist-info/LICENSE
mt3-0.2.1.dist-info/WHEEL
mt3-0.2.1.dist-info/METADATA
mt3-0.2.1.dist-info/RECORD
