Metadata-Version: 2.1
Name: mt3
Version: 0.2.1
Summary: A simple module for outlier detection thanks to Modified Thompson Tau Test
Home-page: https://gitlab.com/h4c5/mt3
License: MIT
Keywords: statistics,outliers,modified thompson tau test
Author: h4c5
Author-email: hakimcheikh@yahoo.fr
Requires-Python: >=3.8,<3.11
Classifier: License :: OSI Approved :: MIT License
Classifier: Programming Language :: Python :: 3
Classifier: Programming Language :: Python :: 3.10
Classifier: Programming Language :: Python :: 3.8
Classifier: Programming Language :: Python :: 3.9
Provides-Extra: numpy
Provides-Extra: pandas
Provides-Extra: scipy
Requires-Dist: numpy (>=1.22.4,<2.0.0); extra == "numpy"
Requires-Dist: pandas (>=1.4.2,<2.0.0); extra == "pandas"
Requires-Dist: scipy (>=1.8.1,<2.0.0); extra == "scipy"
Project-URL: Repository, https://gitlab.com/h4c5/mt3
